jpstock/__init__.py
jpstock/brand.py
jpstock/finance.py
jpstock/historicalprices.py
jpstock/price.py
jpstock/pricebase.py
jpstock/search.py
jpstock/util.py
jpstock/sbi/__init__.py
jpstocks/__init__.py
jpstocks/brand.py
jpstocks/exceptions.py
jpstocks/finance.py
jpstocks/hello.py
jpstocks/historicalprices.py
jpstocks/price.py
jpstocks/pricebase.py
jpstocks/search.py
jpstocks/util.py
jpstocks/sbi/__init__.py
jpstocks-0.5.1.dist-info/LICENSE
jpstocks-0.5.1.dist-info/METADATA
jpstocks-0.5.1.dist-info/WHEEL
jpstocks-0.5.1.dist-info/top_level.txt
jpstocks-0.5.1.dist-info/RECORD
