Metadata-Version: 2.1
Name: jpstocks
Version: 0.5.1
Summary: pip install test
Home-page: https://github.com/robotbatbai
Author: robotbatbai
Author-email: robotbatbai@gmail.com
License: UNKNOWN
Keywords: pip,hello,hello world
Platform: any
Requires-Dist: beautifulsoup4
Requires-Dist: html5lib
